[
    {
        "referent": [
            "CLEVR_000003.png"
        ],
        "type": "embedded implicature (compositional)",
        "utterance": "Exactly one small blue metal cylinder has some of the large yellow metal spheres behind it"
    },
    {
        "image_filename": "CLEVR_000003.png",
        "relationships": {
            "right": [
                [
                    2,
                    4
                ],
                [
                    0,
                    2,
                    4
                ],
                [],
                [
                    0,
                    1,
                    2,
                    4,
                    5,
                    6
                ],
                [
                    2
                ],
                [
                    0,
                    1,
                    2,
                    4,
                    6
                ],
                [
                    0,
                    1,
                    2,
                    4
                ]
            ],
            "left": [
                [
                    1,
                    3,
                    5,
                    6
                ],
                [
                    3,
                    5,
                    6
                ],
                [
                    0,
                    1,
                    3,
                    4,
                    5,
                    6
                ],
                [],
                [
                    0,
                    1,
                    3,
                    5,
                    6
                ],
                [
                    3
                ],
                [
                    3,
                    5
                ]
            ],
            "behind": [
                [],
                [
                    0,
                    2,
                    3,
                    4,
                    6
                ],
                [
                    0
                ],
                [
                    0,
                    2,
                    6
                ],
                [
                    0,
                    2,
                    3,
                    6
                ],
                [
                    0,
                    1,
                    2,
                    3,
                    4,
                    6
                ],
                [
                    0,
                    2
                ]
            ],
            "front": [
                [
                    1,
                    2,
                    3,
                    4,
                    5,
                    6
                ],
                [
                    5
                ],
                [
                    1,
                    3,
                    4,
                    5,
                    6
                ],
                [
                    1,
                    4,
                    5
                ],
                [
                    1,
                    5
                ],
                [],
                [
                    1,
                    3,
                    4,
                    5
                ]
            ]
        },
        "utterances": [
            "some_some_right",
            "one_some_some_front",
            "one_some_all_right",
            "some_all_behind"
        ],
        "directions": {
            "below": [
                -0.0,
                -0.0,
                -1.0
            ],
            "behind": [
                -0.754490315914154,
                0.6563112735748291,
                0.0
            ],
            "right": [
                0.6563112735748291,
                0.7544902563095093,
                -0.0
            ],
            "front": [
                0.754490315914154,
                -0.6563112735748291,
                -0.0
            ],
            "left": [
                -0.6563112735748291,
                -0.7544902563095093,
                0.0
            ],
            "above": [
                0.0,
                0.0,
                1.0
            ]
        },
        "objects": [
            {
                "material": "metal",
                "rotation": 106.62765966385967,
                "size": "small",
                "color": "blue",
                "pixel_coords": [
                    294,
                    103,
                    12.65134048461914
                ],
                "shape": "cylinder",
                "3d_coords": [
                    -0.8719885945320129,
                    2.412933111190796,
                    0.3499999940395355
                ],
                "mask": {
                    "size": [
                        320,
                        480
                    ],
                    "counts": "kXg2j0R95O1N2O0O101O000O101O000000000000000001N1000001N100O2N2K5Ae[e1"
                }
            },
            {
                "material": "metal",
                "rotation": 169.98973078364136,
                "size": "small",
                "color": "blue",
                "pixel_coords": [
                    241,
                    196,
                    9.034515380859375
                ],
                "shape": "cylinder",
                "3d_coords": [
                    1.4781980514526367,
                    -1.221164345741272,
                    0.3499999940395355
                ],
                "mask": {
                    "size": [
                        320,
                        480
                    ],
                    "counts": "amT2m0R9;E3M2N2N101N2O000O2O000O2O0000000000000000000000000001N1000001N101N101N1O2N2M4LaXT2"
                }
            },
            {
                "material": "metal",
                "rotation": 139.78597160323352,
                "size": "small",
                "color": "blue",
                "pixel_coords": [
                    375,
                    125,
                    11.558521270751953
                ],
                "shape": "cylinder",
                "3d_coords": [
                    1.1694151163101196,
                    2.90777325630188,
                    0.3499999940395355
                ],
                "mask": {
                    "size": [
                        320,
                        480
                    ],
                    "counts": "ac`38c95O2N101N2O001O1N2O1O001O2N1O1O1O2N2O0O3M3M0001O000O2O0O1N3I7I6I9Hghj0"
                }
            },
            {
                "material": "metal",
                "rotation": 173.36740374416536,
                "size": "large",
                "color": "yellow",
                "pixel_coords": [
                    79,
                    135,
                    10.309842109680176
                ],
                "shape": "sphere",
                "3d_coords": [
                    -1.8205164670944214,
                    -2.5930299758911133,
                    0.699999988079071
                ],
                "mask": {
                    "size": [
                        320,
                        480
                    ],
                    "counts": "Rn<:a99I6K5K4L3N3M2M3N3M2N2N101N2N2N2O0O2O0O2O0O2O001N10001N100000001O0000000000000000000000O101O00001N10001N101N101N101N2N101N2N2N2N2N2N2N3M2M4L4L4L5J8FRda3"
                }
            },
            {
                "material": "metal",
                "rotation": 275.15909143021787,
                "size": "large",
                "color": "yellow",
                "pixel_coords": [
                    343,
                    156,
                    9.570281982421875
                ],
                "shape": "sphere",
                "3d_coords": [
                    2.062072277069092,
                    0.7343578338623047,
                    0.699999988079071
                ],
                "mask": {
                    "size": [
                        320,
                        480
                    ],
                    "counts": "e^o2>^98I6K4L4L4L3N3M2N2N2N2N2N2N2N2N101N2O0O2O0O2O0O2O0O101O000O101O000000000O10000001O00000000000O2O00000O2O001N100O2O0O2O1N1O2O1N2N2N1O2N3M2N2N2M4M3L3M5K5J7H_Un0"
                }
            },
            {
                "material": "metal",
                "rotation": 159.211445582473,
                "size": "large",
                "color": "yellow",
                "pixel_coords": [
                    165,
                    196,
                    8.406496047973633
                ],
                "shape": "sphere",
                "3d_coords": [
                    1.10334312915802,
                    -2.4868977069854736,
                    0.699999988079071
                ],
                "mask": {
                    "size": [
                        320,
                        480
                    ],
                    "counts": "oeU1:a9;F7K5J5L4M3L3N3L3N2N2N2N2N2N2N2N2O1N1O2O1N1O2O0O2O0O2O000O2O000O101O00000O101O000000000000000000O10001O00000O101O0O101O0O2O0O101N2O0O2O0O2N2N2O0O2N2N2N2N2N3L3N2N3L4L4L4L5J6J9DW`d2"
                }
            },
            {
                "material": "rubber",
                "rotation": 293.40744373053246,
                "size": "large",
                "color": "red",
                "pixel_coords": [
                    216,
                    117,
                    11.075801849365234
                ],
                "shape": "cylinder",
                "3d_coords": [
                    -0.7886525392532349,
                    0.006708666682243347,
                    0.699999988079071
                ],
                "mask": {
                    "size": [
                        320,
                        480
                    ],
                    "counts": "gdh16h9d0\\Oc0^Ob0_O5J3M2O1N2O001N2O001N10001N10001O00000O2O00000000000000001O0000000000O10000000000000000O101O000O10001N10001N100O2O0O2N101N2N2M3M4jN^jW2"
                }
            }
        ],
        "split": "new",
        "image_index": "000003"
    },
    {
        "image_filename": "CLEVR_000004.png",
        "relationships": {
            "right": [
                [
                    1,
                    3,
                    4
                ],
                [
                    3
                ],
                [
                    0,
                    1,
                    3,
                    4
                ],
                [],
                [
                    1,
                    3
                ],
                [
                    0,
                    1,
                    2,
                    3,
                    4,
                    6
                ],
                [
                    0,
                    1,
                    2,
                    3,
                    4
                ]
            ],
            "left": [
                [
                    2,
                    5,
                    6
                ],
                [
                    0,
                    2,
                    4,
                    5,
                    6
                ],
                [
                    5,
                    6
                ],
                [
                    0,
                    1,
                    2,
                    4,
                    5,
                    6
                ],
                [
                    0,
                    2,
                    5,
                    6
                ],
                [],
                [
                    5
                ]
            ],
            "behind": [
                [
                    1,
                    2,
                    3,
                    4,
                    5,
                    6
                ],
                [],
                [
                    1
                ],
                [
                    1,
                    2,
                    6
                ],
                [
                    1,
                    2,
                    3,
                    5,
                    6
                ],
                [
                    1,
                    2,
                    3,
                    6
                ],
                [
                    1,
                    2
                ]
            ],
            "front": [
                [],
                [
                    0,
                    2,
                    3,
                    4,
                    5,
                    6
                ],
                [
                    0,
                    3,
                    4,
                    5,
                    6
                ],
                [
                    0,
                    4,
                    5
                ],
                [
                    0
                ],
                [
                    0,
                    4
                ],
                [
                    0,
                    3,
                    4,
                    5
                ]
            ]
        },
        "utterances": [
            "one_some_some_right",
            "some_some_left",
            "some_all_behind",
            "one_some_all_front"
        ],
        "directions": {
            "below": [
                -0.0,
                -0.0,
                -1.0
            ],
            "behind": [
                -0.754490315914154,
                0.6563112735748291,
                0.0
            ],
            "right": [
                0.6563112735748291,
                0.7544902563095093,
                -0.0
            ],
            "front": [
                0.754490315914154,
                -0.6563112735748291,
                -0.0
            ],
            "left": [
                -0.6563112735748291,
                -0.7544902563095093,
                0.0
            ],
            "above": [
                0.0,
                0.0,
                1.0
            ]
        },
        "objects": [
            {
                "material": "metal",
                "rotation": 150.61669331545883,
                "size": "small",
                "color": "blue",
                "pixel_coords": [
                    267,
                    239,
                    8.169817924499512
                ],
                "shape": "cylinder",
                "3d_coords": [
                    2.7760426998138428,
                    -1.836849331855774,
                    0.3499999940395355
                ],
                "mask": {
                    "size": [
                        320,
                        480
                    ],
                    "counts": "T_\\2n0h8=K4M2N2N2O0O2N2O001N101O0O10001O0000000000000000000000000001N10001N100O2O0O2O0O2N2N2M3K6]OfUk1"
                }
            },
            {
                "material": "metal",
                "rotation": 157.65087587159104,
                "size": "small",
                "color": "blue",
                "pixel_coords": [
                    354,
                    119,
                    12.334388732910156
                ],
                "shape": "cylinder",
                "3d_coords": [
                    0.6825822591781616,
                    2.952979803085327,
                    0.3499999940395355
                ],
                "mask": {
                    "size": [
                        320,
                        480
                    ],
                    "counts": "lgY39]9;E;M201N101N10001O00000000000000000000000001O000O101N101M2J7G9GonQ1"
                }
            },
            {
                "material": "metal",
                "rotation": 212.29972850441985,
                "size": "small",
                "color": "blue",
                "pixel_coords": [
                    235,
                    128,
                    11.85441780090332
                ],
                "shape": "cylinder",
                "3d_coords": [
                    -0.737048327922821,
                    0.47175267338752747,
                    0.3499999940395355
                ],
                "mask": {
                    "size": [
                        320,
                        480
                    ],
                    "counts": "aaT2n0Q93M2O0O2O0O2O0000001O0O10000000000001O000O1000001N101N101N2MahW2"
                }
            },
            {
                "material": "metal",
                "rotation": 280.86935889469623,
                "size": "large",
                "color": "yellow",
                "pixel_coords": [
                    409,
                    146,
                    10.27980899810791
                ],
                "shape": "sphere",
                "3d_coords": [
                    2.7155542373657227,
                    2.035498857498169,
                    0.699999988079071
                ],
                "mask": {
                    "size": [
                        320,
                        480
                    ],
                    "counts": "`\\d34f9=E7K4L4L4M3L3N2N2N2N2N2N2N2N2O0O2N2O0O2O0O101N101O0O10001O000O1000001O00000000O100000001O000O101O0O101O0O101N101N2O0O2N2O0O2N2N2N2N2N2N3L3N3L4L4K7I8Fgk9"
                }
            },
            {
                "material": "metal",
                "rotation": 52.57210326824692,
                "size": "large",
                "color": "yellow",
                "pixel_coords": [
                    301,
                    180,
                    9.11536979675293
                ],
                "shape": "sphere",
                "3d_coords": [
                    2.243438482284546,
                    -0.5320402979850769,
                    0.699999988079071
                ],
                "mask": {
                    "size": [
                        320,
                        480
                    ],
                    "counts": "\\ga2?]98I6K4L4L4L4M2M4M2N2N2N2N1O2O0O1O2O0O1O2O0O2O0O2O1O1N2O1O1N100000001N10000000000000000001O000O10001O000O101O0O2O0O101N2O0O2O0O2N2O1N2N1O2N3M2N2N2M4M2M4L4L5K5J7HgnZ1"
                }
            },
            {
                "material": "metal",
                "rotation": 67.51152787797625,
                "size": "large",
                "color": "yellow",
                "pixel_coords": [
                    123,
                    163,
                    9.665178298950195
                ],
                "shape": "sphere",
                "3d_coords": [
                    -0.3223302364349365,
                    -2.558886766433716,
                    0.699999988079071
                ],
                "mask": {
                    "size": [
                        320,
                        480
                    ],
                    "counts": "k\\j0`0\\97J6K4L4M3L3N3L3N2N2N2N2N2O1N1O2O1N1O2O0O2O001N100O2O00001N10000000001O000000000000O100000001O0O10001O0O101N101N101N101N2N101N2N2N2N2N2N2N3M2M4L3N4K4K6J9DWWS3"
                }
            },
            {
                "material": "metal",
                "rotation": 249.85928648096873,
                "size": "small",
                "color": "red",
                "pixel_coords": [
                    186,
                    140,
                    11.33775806427002
                ],
                "shape": "cube",
                "3d_coords": [
                    -0.9797989726066589,
                    -0.7061084508895874,
                    0.3499999940395355
                ],
                "mask": {
                    "size": [
                        320,
                        480
                    ],
                    "counts": "nQc1:e9>C5J101N101O0O2O001N101N101O0O2O001N101N100000O2O0O2O0O101O0O2O0O101N101N100O2O001N2Oa0]Ockd2"
                }
            }
        ],
        "split": "new",
        "image_index": "000004"
    },
    {
        "image_filename": "CLEVR_000005.png",
        "relationships": {
            "right": [
                [
                    1,
                    3
                ],
                [
                    3
                ],
                [
                    0,
                    1,
                    3,
                    4,
                    5,
                    6
                ],
                [],
                [
                    0,
                    1,
                    3,
                    5,
                    6
                ],
                [
                    0,
                    1,
                    3,
                    6
                ],
                [
                    0,
                    1,
                    3
                ]
            ],
            "left": [
                [
                    2,
                    4,
                    5,
                    6
                ],
                [
                    0,
                    2,
                    4,
                    5,
                    6
                ],
                [],
                [
                    0,
                    1,
                    2,
                    4,
                    5,
                    6
                ],
                [
                    2
                ],
                [
                    2,
                    4
                ],
                [
                    2,
                    4,
                    5
                ]
            ],
            "behind": [
                [
                    1,
                    2,
                    3,
                    4,
                    5
                ],
                [
                    2,
                    3,
                    5
                ],
                [
                    5
                ],
                [
                    2,
                    5
                ],
                [
                    1,
                    2,
                    3,
                    5
                ],
                [],
                [
                    0,
                    1,
                    2,
                    3,
                    4,
                    5
                ]
            ],
            "front": [
                [
                    6
                ],
                [
                    0,
                    4,
                    6
                ],
                [
                    0,
                    1,
                    3,
                    4,
                    6
                ],
                [
                    0,
                    1,
                    4,
                    6
                ],
                [
                    0,
                    6
                ],
                [
                    0,
                    1,
                    2,
                    3,
                    4,
                    6
                ],
                []
            ]
        },
        "utterances": [
            "some_some_right",
            "one_some_some_behind",
            "one_some_some_front",
            "one_some_all_left",
            "one_some_all_front"
        ],
        "directions": {
            "below": [
                -0.0,
                -0.0,
                -1.0
            ],
            "behind": [
                -0.754490315914154,
                0.6563112735748291,
                0.0
            ],
            "right": [
                0.6563112735748291,
                0.7544902563095093,
                -0.0
            ],
            "front": [
                0.754490315914154,
                -0.6563112735748291,
                -0.0
            ],
            "left": [
                -0.6563112735748291,
                -0.7544902563095093,
                0.0
            ],
            "above": [
                0.0,
                0.0,
                1.0
            ]
        },
        "objects": [
            {
                "material": "metal",
                "rotation": 111.5038441406538,
                "size": "small",
                "color": "blue",
                "pixel_coords": [
                    275,
                    213,
                    9.00951099395752
                ],
                "shape": "cylinder",
                "3d_coords": [
                    2.1516144275665283,
                    -1.101022481918335,
                    0.3499999940395355
                ],
                "mask": {
                    "size": [
                        320,
                        480
                    ],
                    "counts": "Rl_25i92O1O1O100O2N10000O2O00000O2O001O00001O001O1O0010O01O1O1O10O0100O1O2O000O101O01H9^OZPi1"
                }
            },
            {
                "material": "metal",
                "rotation": 314.49436519614983,
                "size": "small",
                "color": "blue",
                "pixel_coords": [
                    307,
                    168,
                    10.266114234924316
                ],
                "shape": "cylinder",
                "3d_coords": [
                    1.52652907371521,
                    0.4055781364440918,
                    0.3499999940395355
                ],
                "mask": {
                    "size": [
                        320,
                        480
                    ],
                    "counts": "T_j2e0n8>M3N2N2N101N10001N10001O000000000000000000000001O0O10001N101N1O2N2M2I9D<Dae_1"
                }
            },
            {
                "material": "metal",
                "rotation": 314.74925825660983,
                "size": "small",
                "color": "blue",
                "pixel_coords": [
                    137,
                    131,
                    11.59616756439209
                ],
                "shape": "cylinder",
                "3d_coords": [
                    -2.0218002796173096,
                    -1.2566944360733032,
                    0.3499999940395355
                ],
                "mask": {
                    "size": [
                        320,
                        480
                    ],
                    "counts": "dYU18g99G8H3NO0100O10O1000O1000O10000000000000000001O0001O0000100O1O3N9F:GfgU3"
                }
            },
            {
                "material": "metal",
                "rotation": 103.50865841790456,
                "size": "large",
                "color": "yellow",
                "pixel_coords": [
                    407,
                    133,
                    10.76237678527832
                ],
                "shape": "sphere",
                "3d_coords": [
                    2.3310916423797607,
                    2.504803419113159,
                    0.699999988079071
                ],
                "mask": {
                    "size": [
                        320,
                        480
                    ],
                    "counts": "n[d3>_97I5L5K3N3L3N2N3M2N2N1O2N2N2O0O2N2O0O2O0O101O0O101O000O101O0000000000000000000000O1000001N10001N10001N101N101N2N1O2O1N2N2N2N2N2N2M4M3L4L4K6JW^;"
                }
            },
            {
                "material": "metal",
                "rotation": 290.4775385453056,
                "size": "large",
                "color": "yellow",
                "pixel_coords": [
                    137,
                    178,
                    9.320947647094727
                ],
                "shape": "sphere",
                "3d_coords": [
                    0.11370912194252014,
                    -2.5341484546661377,
                    0.699999988079071
                ],
                "mask": {
                    "size": [
                        320,
                        480
                    ],
                    "counts": "Z_n0`0\\98I6K4L4L3N3L3N3M2N2N2N2N2N2N101N2N101N101N101N101N10001O0O10001O000O10000000000000000001O000O1000001N10001N101O0O2O0O2N101N2N101N2N2N2N2N2N2N2N3L3N3L4L4K6J8Gi`n2"
                }
            },
            {
                "material": "metal",
                "rotation": 328.99490740052585,
                "size": "large",
                "color": "yellow",
                "pixel_coords": [
                    223,
                    86,
                    12.843169212341309
                ],
                "shape": "sphere",
                "3d_coords": [
                    -2.025461196899414,
                    1.2520908117294312,
                    0.699999988079071
                ],
                "mask": {
                    "size": [
                        320,
                        480
                    ],
                    "counts": "_Pm1=`97I5L4M3L3N2N3M2N1O2N2O1N1O2O1N10001N101O0O1000001O000000000000O101O00000O2O0O2O001N1O2O1N2N1O2N2N3M2N2M4M3L5J7HcUW2"
                }
            },
            {
                "material": "metal",
                "rotation": 171.80354372103952,
                "size": "large",
                "color": "green",
                "pixel_coords": [
                    254,
                    247,
                    7.723412036895752
                ],
                "shape": "sphere",
                "3d_coords": [
                    2.8493294715881348,
                    -2.2596354484558105,
                    0.699999988079071
                ],
                "mask": {
                    "size": [
                        320,
                        480
                    ],
                    "counts": "`cP2?\\9:G7K5J5L4M3L3M4M2N3M2M3N2N2N2O1N2N2N1O2O1N101N2N101N101O0O101N101O000O101O000O1000001O0000000000000000O10001O0000001N10000O2O001N100O2O0O2O1N101N1O2O1N2N2N101N2N2N3L3N2N2N3L3N3L4L4L5J6J7Hffg1"
                }
            }
        ],
        "split": "new",
        "image_index": "000005"
    }
]