[
    {
        "referent": [
            "CLEVR_000024.png"
        ],
        "type": "embedded implicature (compositional)",
        "utterance": "There is exactly one sphere that has some cubes on the right of it"
    },
    {
        "utterances": [
            "some_some_front",
            "one_some_some_right",
            "one_some_some_left",
            "some_some_behind",
            "some_all_right",
            "one_some_all_behind"
        ],
        "image_index": "000024",
        "objects": [
            {
                "size": "large",
                "rotation": 158.82186235801427,
                "color": "purple",
                "3d_coords": [
                    1.549914836883545,
                    0.9144509434700012,
                    0.699999988079071
                ],
                "shape": "sphere",
                "material": "metal",
                "pixel_coords": [
                    328,
                    142,
                    10.287286758422852
                ]
            },
            {
                "size": "small",
                "rotation": 131.08329640969671,
                "color": "gray",
                "3d_coords": [
                    -1.4423096179962158,
                    0.6459921002388,
                    0.3499999940395355
                ],
                "shape": "sphere",
                "material": "metal",
                "pixel_coords": [
                    219,
                    115,
                    12.229228973388672
                ]
            },
            {
                "size": "small",
                "rotation": 58.19660172132529,
                "color": "gray",
                "3d_coords": [
                    1.5182890892028809,
                    -1.0383973121643066,
                    0.3499999940395355
                ],
                "shape": "sphere",
                "material": "metal",
                "pixel_coords": [
                    254,
                    193,
                    9.332295417785645
                ]
            },
            {
                "size": "small",
                "rotation": 146.05705202927922,
                "color": "blue",
                "3d_coords": [
                    0.9641264081001282,
                    -2.352247476577759,
                    0.3499999940395355
                ],
                "shape": "cube",
                "material": "metal",
                "pixel_coords": [
                    176,
                    208,
                    8.917841911315918
                ]
            },
            {
                "size": "large",
                "rotation": 52.04201022840125,
                "color": "red",
                "3d_coords": [
                    -2.743187427520752,
                    0.1884632408618927,
                    0.699999988079071
                ],
                "shape": "cube",
                "material": "metal",
                "pixel_coords": [
                    169,
                    91,
                    12.627391815185547
                ]
            },
            {
                "size": "small",
                "rotation": 57.47871421121874,
                "color": "yellow",
                "3d_coords": [
                    -2.2055160999298096,
                    -2.1506752967834473,
                    0.3499999940395355
                ],
                "shape": "cube",
                "material": "rubber",
                "pixel_coords": [
                    94,
                    141,
                    11.078703880310059
                ]
            },
            {
                "size": "small",
                "rotation": 149.6845335933519,
                "color": "blue",
                "3d_coords": [
                    -0.6660473346710205,
                    -2.5728211402893066,
                    0.3499999940395355
                ],
                "shape": "sphere",
                "material": "rubber",
                "pixel_coords": [
                    115,
                    176,
                    9.838780403137207
                ]
            },
            {
                "size": "small",
                "rotation": 100.05670704105664,
                "color": "purple",
                "3d_coords": [
                    -2.3480823040008545,
                    2.9476263523101807,
                    0.3499999940395355
                ],
                "shape": "sphere",
                "material": "rubber",
                "pixel_coords": [
                    262,
                    81,
                    14.16452407836914
                ]
            }
        ],
        "directions": {
            "front": [
                0.754490315914154,
                -0.6563112735748291,
                -0.0
            ],
            "above": [
                0.0,
                0.0,
                1.0
            ],
            "behind": [
                -0.754490315914154,
                0.6563112735748291,
                0.0
            ],
            "below": [
                -0.0,
                -0.0,
                -1.0
            ],
            "right": [
                0.6563112735748291,
                0.7544902563095093,
                -0.0
            ],
            "left": [
                -0.6563112735748291,
                -0.7544902563095093,
                0.0
            ]
        },
        "split": "new",
        "image_filename": "CLEVR_000024.png",
        "relationships": {
            "front": [
                [
                    2,
                    3,
                    6
                ],
                [
                    0,
                    2,
                    3,
                    5,
                    6
                ],
                [
                    3
                ],
                [],
                [
                    0,
                    1,
                    2,
                    3,
                    5,
                    6
                ],
                [
                    0,
                    2,
                    3,
                    6
                ],
                [
                    2,
                    3
                ],
                [
                    0,
                    1,
                    2,
                    3,
                    4,
                    5,
                    6
                ]
            ],
            "right": [
                [],
                [
                    0,
                    2,
                    7
                ],
                [
                    0,
                    7
                ],
                [
                    0,
                    1,
                    2,
                    7
                ],
                [
                    0,
                    1,
                    2,
                    3,
                    7
                ],
                [
                    0,
                    1,
                    2,
                    3,
                    4,
                    6,
                    7
                ],
                [
                    0,
                    1,
                    2,
                    3,
                    4,
                    7
                ],
                [
                    0
                ]
            ],
            "left": [
                [
                    1,
                    2,
                    3,
                    4,
                    5,
                    6,
                    7
                ],
                [
                    3,
                    4,
                    5,
                    6
                ],
                [
                    1,
                    3,
                    4,
                    5,
                    6
                ],
                [
                    4,
                    5,
                    6
                ],
                [
                    5,
                    6
                ],
                [],
                [
                    5
                ],
                [
                    1,
                    2,
                    3,
                    4,
                    5,
                    6
                ]
            ],
            "behind": [
                [
                    1,
                    4,
                    5,
                    7
                ],
                [
                    4,
                    7
                ],
                [
                    0,
                    1,
                    4,
                    5,
                    6,
                    7
                ],
                [
                    0,
                    1,
                    2,
                    4,
                    5,
                    6,
                    7
                ],
                [
                    7
                ],
                [
                    1,
                    4,
                    7
                ],
                [
                    0,
                    1,
                    4,
                    5,
                    7
                ],
                []
            ]
        }
    },
    {
        "utterances": [
            "one_all_all_left",
            "one_all_some_behind",
            "one_all_some_front"
        ],
        "image_index": "000025",
        "objects": [
            {
                "size": "small",
                "rotation": 193.719128484924,
                "color": "gray",
                "3d_coords": [
                    -2.900343894958496,
                    -1.137178897857666,
                    0.3499999940395355
                ],
                "shape": "sphere",
                "material": "metal",
                "pixel_coords": [
                    121,
                    115,
                    12.137961387634277
                ]
            },
            {
                "size": "large",
                "rotation": 307.1205497892905,
                "color": "purple",
                "3d_coords": [
                    1.3846696615219116,
                    2.87955641746521,
                    0.699999988079071
                ],
                "shape": "cube",
                "material": "metal",
                "pixel_coords": [
                    382,
                    113,
                    11.390271186828613
                ]
            },
            {
                "size": "small",
                "rotation": 32.84228098396095,
                "color": "purple",
                "3d_coords": [
                    -0.7660160064697266,
                    2.2633161544799805,
                    0.3499999940395355
                ],
                "shape": "cube",
                "material": "rubber",
                "pixel_coords": [
                    291,
                    105,
                    12.640223503112793
                ]
            },
            {
                "size": "small",
                "rotation": 73.97721451202784,
                "color": "gray",
                "3d_coords": [
                    0.024373633787035942,
                    -0.6279119253158569,
                    0.3499999940395355
                ],
                "shape": "cube",
                "material": "rubber",
                "pixel_coords": [
                    217,
                    155,
                    10.48815631866455
                ]
            },
            {
                "size": "large",
                "rotation": 226.41485936957744,
                "color": "green",
                "3d_coords": [
                    -0.30845171213150024,
                    -2.1035525798797607,
                    0.699999988079071
                ],
                "shape": "cylinder",
                "material": "rubber",
                "pixel_coords": [
                    143,
                    157,
                    9.704333305358887
                ]
            }
        ],
        "directions": {
            "front": [
                0.754490315914154,
                -0.6563112735748291,
                -0.0
            ],
            "above": [
                0.0,
                0.0,
                1.0
            ],
            "behind": [
                -0.754490315914154,
                0.6563112735748291,
                0.0
            ],
            "below": [
                -0.0,
                -0.0,
                -1.0
            ],
            "right": [
                0.6563112735748291,
                0.7544902563095093,
                -0.0
            ],
            "left": [
                -0.6563112735748291,
                -0.7544902563095093,
                0.0
            ]
        },
        "split": "new",
        "image_filename": "CLEVR_000025.png",
        "relationships": {
            "front": [
                [
                    1,
                    3,
                    4
                ],
                [
                    3,
                    4
                ],
                [
                    0,
                    1,
                    3,
                    4
                ],
                [
                    4
                ],
                []
            ],
            "right": [
                [
                    1,
                    2,
                    3,
                    4
                ],
                [],
                [
                    1
                ],
                [
                    1,
                    2
                ],
                [
                    1,
                    2,
                    3
                ]
            ],
            "left": [
                [],
                [
                    0,
                    2,
                    3,
                    4
                ],
                [
                    0,
                    3,
                    4
                ],
                [
                    0,
                    4
                ],
                [
                    0
                ]
            ],
            "behind": [
                [
                    2
                ],
                [
                    0,
                    2
                ],
                [],
                [
                    0,
                    1,
                    2
                ],
                [
                    0,
                    1,
                    2,
                    3
                ]
            ]
        }
    },
    {
        "utterances": [
            "all_some_front",
            "one_some_some_right",
            "one_some_some_left",
            "all_some_behind",
            "some_all_left"
        ],
        "image_index": "000026",
        "objects": [
            {
                "size": "small",
                "rotation": 299.6842366442989,
                "color": "green",
                "3d_coords": [
                    -1.5601600408554077,
                    -0.6519463062286377,
                    0.3499999940395355
                ],
                "shape": "sphere",
                "material": "metal",
                "pixel_coords": [
                    174,
                    130,
                    11.861861228942871
                ]
            },
            {
                "size": "small",
                "rotation": 282.68906598357705,
                "color": "gray",
                "3d_coords": [
                    1.9153305292129517,
                    1.3232990503311157,
                    0.3499999940395355
                ],
                "shape": "cube",
                "material": "metal",
                "pixel_coords": [
                    351,
                    160,
                    10.628782272338867
                ]
            },
            {
                "size": "small",
                "rotation": 241.8733988947749,
                "color": "gray",
                "3d_coords": [
                    -1.3660037517547607,
                    1.8343664407730103,
                    0.3499999940395355
                ],
                "shape": "cube",
                "material": "metal",
                "pixel_coords": [
                    262,
                    104,
                    13.118877410888672
                ]
            },
            {
                "size": "small",
                "rotation": 226.0106896785038,
                "color": "blue",
                "3d_coords": [
                    -0.6044278740882874,
                    -0.3113803267478943,
                    0.3499999940395355
                ],
                "shape": "cube",
                "material": "metal",
                "pixel_coords": [
                    211,
                    140,
                    11.409708023071289
                ]
            },
            {
                "size": "small",
                "rotation": 304.5758371952222,
                "color": "gray",
                "3d_coords": [
                    2.483403205871582,
                    -0.8038314580917358,
                    0.3499999940395355
                ],
                "shape": "cube",
                "material": "metal",
                "pixel_coords": [
                    296,
                    211,
                    9.060027122497559
                ]
            },
            {
                "size": "small",
                "rotation": 49.60024240451414,
                "color": "gray",
                "3d_coords": [
                    -0.3752135932445526,
                    -2.518334150314331,
                    0.3499999940395355
                ],
                "shape": "sphere",
                "material": "rubber",
                "pixel_coords": [
                    126,
                    178,
                    10.024104118347168
                ]
            },
            {
                "size": "large",
                "rotation": 95.00832807342802,
                "color": "red",
                "3d_coords": [
                    -2.8815505504608154,
                    1.0493755340576172,
                    0.699999988079071
                ],
                "shape": "cube",
                "material": "metal",
                "pixel_coords": [
                    200,
                    82,
                    13.528775215148926
                ]
            },
            {
                "size": "small",
                "rotation": 298.08675960412427,
                "color": "purple",
                "3d_coords": [
                    1.3866227865219116,
                    -1.218571662902832,
                    0.3499999940395355
                ],
                "shape": "sphere",
                "material": "metal",
                "pixel_coords": [
                    237,
                    193,
                    9.56556510925293
                ]
            }
        ],
        "directions": {
            "front": [
                0.754490315914154,
                -0.6563112735748291,
                -0.0
            ],
            "above": [
                0.0,
                0.0,
                1.0
            ],
            "behind": [
                -0.754490315914154,
                0.6563112735748291,
                0.0
            ],
            "below": [
                -0.0,
                -0.0,
                -1.0
            ],
            "right": [
                0.6563112735748291,
                0.7544902563095093,
                -0.0
            ],
            "left": [
                -0.6563112735748291,
                -0.7544902563095093,
                0.0
            ]
        },
        "split": "new",
        "image_filename": "CLEVR_000026.png",
        "relationships": {
            "front": [
                [
                    1,
                    3,
                    4,
                    5,
                    7
                ],
                [
                    4,
                    5,
                    7
                ],
                [
                    0,
                    1,
                    3,
                    4,
                    5,
                    7
                ],
                [
                    1,
                    4,
                    5,
                    7
                ],
                [],
                [
                    4,
                    7
                ],
                [
                    0,
                    1,
                    2,
                    3,
                    4,
                    5,
                    7
                ],
                [
                    4
                ]
            ],
            "right": [
                [
                    1,
                    2,
                    3,
                    4,
                    6,
                    7
                ],
                [],
                [
                    1,
                    4
                ],
                [
                    1,
                    2,
                    4,
                    7
                ],
                [
                    1
                ],
                [
                    0,
                    1,
                    2,
                    3,
                    4,
                    6,
                    7
                ],
                [
                    1,
                    2,
                    3,
                    4,
                    7
                ],
                [
                    1,
                    2,
                    4
                ]
            ],
            "left": [
                [
                    5
                ],
                [
                    0,
                    2,
                    3,
                    4,
                    5,
                    6,
                    7
                ],
                [
                    0,
                    3,
                    5,
                    6,
                    7
                ],
                [
                    0,
                    5,
                    6
                ],
                [
                    0,
                    2,
                    3,
                    5,
                    6,
                    7
                ],
                [],
                [
                    0,
                    5
                ],
                [
                    0,
                    3,
                    5,
                    6
                ]
            ],
            "behind": [
                [
                    2,
                    6
                ],
                [
                    0,
                    2,
                    3,
                    6
                ],
                [
                    6
                ],
                [
                    0,
                    2,
                    6
                ],
                [
                    0,
                    1,
                    2,
                    3,
                    5,
                    6,
                    7
                ],
                [
                    0,
                    1,
                    2,
                    3,
                    6
                ],
                [],
                [
                    0,
                    1,
                    2,
                    3,
                    5,
                    6
                ]
            ]
        }
    }
]