[
    {
        "utterance": "There are white kites or lying snowboards in the images",
        "type": "direct contextual cancellation",
        "referents": [
            "000000085911.jpg",
            "000000428454.jpg"
        ]
    },
    {
        "image_filename": "000000085911.jpg"
    },
    {
        "image_filename": "000000428454.jpg"
    },
    {
        "image_filename": "000000221291.jpg"
    },
    {
        "image_filename": "000000039914.jpg"
    },
    {
        "image_filename": "000000529939.jpg"
    }
]