[
    {
        "utterance": "Not all small yellow objects are rubber.",
        "type": "indirect implicature",
        "referent": [
            "CLEVR_000033.png"
        ]
    },
    {
        "relationships": {
            "front": [
                [
                    1,
                    2,
                    4
                ],
                [
                    2
                ],
                [],
                [
                    0,
                    1,
                    2,
                    4
                ],
                [
                    1,
                    2
                ]
            ],
            "behind": [
                [
                    3
                ],
                [
                    0,
                    3,
                    4
                ],
                [
                    0,
                    1,
                    3,
                    4
                ],
                [],
                [
                    0,
                    3
                ]
            ],
            "right": [
                [
                    1,
                    2,
                    3
                ],
                [],
                [
                    1,
                    3
                ],
                [
                    1
                ],
                [
                    0,
                    1,
                    2,
                    3
                ]
            ],
            "left": [
                [
                    4
                ],
                [
                    0,
                    2,
                    3,
                    4
                ],
                [
                    0,
                    4
                ],
                [
                    0,
                    2,
                    4
                ],
                []
            ]
        },
        "objects": [
            {
                "size": "small",
                "material": "metal",
                "3d_coords": [
                    -1.6745035648345947,
                    -0.4490053653717041,
                    0.3499999940395355
                ],
                "shape": "cylinder",
                "color": "yellow",
                "rotation": 342.67474562147555,
                "pixel_coords": [
                    179,
                    126,
                    11.897310256958008
                ],
                "mask": {
                    "size": [
                        320,
                        480
                    ],
                    "counts": "`gb13k9`0A=D1N2O1N101O00000O2O00000000000000000000O101O000O101O0O2N2Ob0\\ORnh2"
                }
            },
            {
                "size": "small",
                "material": "metal",
                "3d_coords": [
                    1.9635566473007202,
                    0.591834306716919,
                    0.3499999940395355
                ],
                "shape": "cylinder",
                "color": "yellow",
                "rotation": 31.729356376783112,
                "pixel_coords": [
                    329,
                    171,
                    9.906755447387695
                ],
                "mask": {
                    "size": [
                        320,
                        480
                    ],
                    "counts": "dgP38Y9a0B=M3O0O2N101N101O00001N100000000000001O0000O101O0000001N10000O2O0O2N2N1I8F:E`iX1"
                }
            },
            {
                "size": "small",
                "material": "rubber",
                "3d_coords": [
                    1.4316798448562622,
                    -2.418754816055298,
                    0.3499999940395355
                ],
                "shape": "cube",
                "color": "yellow",
                "rotation": 341.9561699193479,
                "pixel_coords": [
                    178,
                    212,
                    8.62243366241455
                ],
                "mask": {
                    "size": [
                        320,
                        480
                    ],
                    "counts": "mY`15i9>D<C=D:F1O1O0000000O100000000000O1000000000O100000O10000000000000O10O100000001O1O2N5K4K5L8Gaof2"
                }
            },
            {
                "size": "large",
                "material": "rubber",
                "3d_coords": [
                    -2.757328510284424,
                    2.9038522243499756,
                    0.699999988079071
                ],
                "shape": "sphere",
                "color": "gray",
                "rotation": 311.91957480793263,
                "pixel_coords": [
                    262,
                    72,
                    14.352015495300293
                ],
                "mask": {
                    "size": [
                        320,
                        480
                    ],
                    "counts": "SjY2;a97K5K3N3L3N3M2N2N1O2O1N2N101N101O0O10001O0O1000000000000001O0O10001N101O0O2O0O2N2N2O0O2N3L3N3M2M5J6JQXl1"
                }
            },
            {
                "size": "small",
                "material": "rubber",
                "3d_coords": [
                    -2.87968373298645,
                    -2.7587432861328125,
                    0.3499999940395355
                ],
                "shape": "cube",
                "color": "red",
                "rotation": 184.9895159762503,
                "pixel_coords": [
                    59,
                    134,
                    11.473800659179688
                ],
                "mask": {
                    "size": [
                        320,
                        480
                    ],
                    "counts": "hc<<a99I6K5K6I2O1O00000000O100000O10000000O1000000000O1000O10000000002N5K6I8I7He_m3"
                }
            }
        ],
        "directions": {
            "right": [
                0.6563112735748291,
                0.7544902563095093,
                -0.0
            ],
            "above": [
                0.0,
                0.0,
                1.0
            ],
            "below": [
                -0.0,
                -0.0,
                -1.0
            ],
            "front": [
                0.754490315914154,
                -0.6563112735748291,
                -0.0
            ],
            "behind": [
                -0.754490315914154,
                0.6563112735748291,
                0.0
            ],
            "left": [
                -0.6563112735748291,
                -0.7544902563095093,
                0.0
            ]
        },
        "split": "new",
        "image_filename": "CLEVR_000033.png",
        "image_index": "000033"
    },
    {
        "relationships": {
            "front": [
                [
                    1
                ],
                [],
                [
                    0,
                    1
                ],
                [
                    0,
                    1,
                    2
                ]
            ],
            "behind": [
                [
                    2,
                    3
                ],
                [
                    0,
                    2,
                    3
                ],
                [
                    3
                ],
                []
            ],
            "right": [
                [],
                [
                    0,
                    2
                ],
                [
                    0
                ],
                [
                    0,
                    1,
                    2
                ]
            ],
            "left": [
                [
                    1,
                    2,
                    3
                ],
                [
                    3
                ],
                [
                    1,
                    3
                ],
                []
            ]
        },
        "objects": [
            {
                "size": "small",
                "material": "rubber",
                "3d_coords": [
                    2.5014026165008545,
                    -0.8724929094314575,
                    0.3499999940395355
                ],
                "shape": "cube",
                "color": "yellow",
                "rotation": 141.07003496459393,
                "pixel_coords": [
                    297,
                    200,
                    9.245497703552246
                ],
                "mask": {
                    "size": [
                        320,
                        480
                    ],
                    "counts": "ikd2k0P96N2N2O1O1O1O1N3N1O1O1O1N2O1O1O001N1000000O01000000O0100000O1000000O2O1O1O0O2O1O1O0O2O1O1O1N101O1N2N2G9Bab`1"
                }
            },
            {
                "size": "small",
                "material": "rubber",
                "3d_coords": [
                    1.6655353307724,
                    -2.6707231998443604,
                    0.3499999940395355
                ],
                "shape": "cylinder",
                "color": "yellow",
                "rotation": 116.39169925230401,
                "pixel_coords": [
                    186,
                    217,
                    8.735346794128418
                ],
                "mask": {
                    "size": [
                        320,
                        480
                    ],
                    "counts": "WTc15i9`0A?A7I3M2N2O001N101N101O000O10001O000000000000000000O100000001N10000O2O0O2O1N1O2N3M;DdSe2"
                }
            },
            {
                "size": "small",
                "material": "rubber",
                "3d_coords": [
                    -0.04746337607502937,
                    -0.1244000494480133,
                    0.3499999940395355
                ],
                "shape": "cube",
                "color": "yellow",
                "rotation": 199.0545826072413,
                "pixel_coords": [
                    234,
                    146,
                    11.432045936584473
                ],
                "mask": {
                    "size": [
                        320,
                        480
                    ],
                    "counts": "QZS2a0^9<E1O2N2N1N3N2N1O000000000000O010000000000000O10O10000001O002M2O1O1O1O2N1N2Mj_V2"
                }
            },
            {
                "size": "small",
                "material": "rubber",
                "3d_coords": [
                    -2.8847415447235107,
                    -0.5553299784660339,
                    0.3499999940395355
                ],
                "shape": "cylinder",
                "color": "green",
                "rotation": 172.05754210421645,
                "pixel_coords": [
                    147,
                    117,
                    13.107146263122559
                ],
                "mask": {
                    "size": [
                        320,
                        480
                    ],
                    "counts": "W[Y1=c9;D6K1N2O000O2O00000000000000000000000000O10001O0O2O0O7J?_OWXS3"
                }
            }
        ],
        "directions": {
            "right": [
                0.6563112735748291,
                0.7544902563095093,
                -0.0
            ],
            "above": [
                0.0,
                0.0,
                1.0
            ],
            "below": [
                -0.0,
                -0.0,
                -1.0
            ],
            "front": [
                0.754490315914154,
                -0.6563112735748291,
                -0.0
            ],
            "behind": [
                -0.754490315914154,
                0.6563112735748291,
                0.0
            ],
            "left": [
                -0.6563112735748291,
                -0.7544902563095093,
                0.0
            ]
        },
        "split": "new",
        "image_filename": "CLEVR_000034.png",
        "image_index": "000034"
    },
    {
        "relationships": {
            "front": [
                [
                    1
                ],
                [],
                [
                    0,
                    1
                ],
                [
                    0,
                    1,
                    2
                ]
            ],
            "behind": [
                [
                    2,
                    3
                ],
                [
                    0,
                    2,
                    3
                ],
                [
                    3
                ],
                []
            ],
            "right": [
                [],
                [
                    0,
                    3
                ],
                [
                    0,
                    1,
                    3
                ],
                [
                    0
                ]
            ],
            "left": [
                [
                    1,
                    2,
                    3
                ],
                [
                    2
                ],
                [],
                [
                    1,
                    2
                ]
            ]
        },
        "objects": [
            {
                "size": "large",
                "material": "rubber",
                "3d_coords": [
                    2.7870359420776367,
                    0.1442074179649353,
                    0.699999988079071
                ],
                "shape": "cube",
                "color": "purple",
                "rotation": 330.83356015512913,
                "pixel_coords": [
                    350,
                    174,
                    9.434645652770996
                ],
                "mask": {
                    "size": [
                        320,
                        480
                    ],
                    "counts": "bkn2=S9b0^Ob0A?K5M3M3N3L3N2N2N2N2N2N2N2N2N1O1N2O1O000000000000000000000000O10000000O1000000000000000O100000000000000000O100000O1000000000000000000000000O2O001O1O1O1O1O1O1O1O1O1N2O1O1O1O1O2M2N2N2M3I7I7I7H8I7I7H8I9GZof0"
                }
            },
            {
                "size": "large",
                "material": "metal",
                "3d_coords": [
                    2.4259860515594482,
                    -2.0714359283447266,
                    0.699999988079071
                ],
                "shape": "cube",
                "color": "purple",
                "rotation": 107.15374449204488,
                "pixel_coords": [
                    247,
                    211,
                    8.338214874267578
                ],
                "mask": {
                    "size": [
                        320,
                        480
                    ],
                    "counts": "hcj1b0\\9e0[Oe0]O<C3M2N2N101N1O2N1O101N1O1O2O0O1O2N1O101N1O1O2O0O1O2N1O101N1O1O2O0O1O2N1O2O0O101N10001O00010O000010O0001O01O01O000010O0001O01O01O00010O00001O01O0000001O0O100O2N1N2O1O1N3N1O1N2O2N1N2O1O2M2O1O1N2O2N1N2O1O2M2O1O1N3N1O1N2O2M2G:_Oa0_Oc0]OVkf1"
                }
            },
            {
                "size": "small",
                "material": "rubber",
                "3d_coords": [
                    -2.699544906616211,
                    -1.574683666229248,
                    0.3499999940395355
                ],
                "shape": "cylinder",
                "color": "red",
                "rotation": 134.19354168496085,
                "pixel_coords": [
                    111,
                    128,
                    12.17751407623291
                ],
                "mask": {
                    "size": [
                        320,
                        480
                    ],
                    "counts": "c_m05j98H9G8I3L2O1O0O101O00000O1000000000000000000001N10000O2O001N4L;F9Elk]3"
                }
            },
            {
                "size": "large",
                "material": "rubber",
                "3d_coords": [
                    -1.419528841972351,
                    2.9809041023254395,
                    0.699999988079071
                ],
                "shape": "sphere",
                "color": "yellow",
                "rotation": 172.11057655057508,
                "pixel_coords": [
                    287,
                    85,
                    13.919918060302734
                ],
                "mask": {
                    "size": [
                        320,
                        480
                    ],
                    "counts": "^da2>_96K4L4L3N3M2N2N2N1O2N2O1N101N100O2O000O2O00000000000000000000O101O000O2O0O2O0O2O1N1O2N2N2N2N2N3L4M3L5J8Edic1"
                }
            }
        ],
        "directions": {
            "right": [
                0.6563112735748291,
                0.7544902563095093,
                -0.0
            ],
            "above": [
                0.0,
                0.0,
                1.0
            ],
            "below": [
                -0.0,
                -0.0,
                -1.0
            ],
            "front": [
                0.754490315914154,
                -0.6563112735748291,
                -0.0
            ],
            "behind": [
                -0.754490315914154,
                0.6563112735748291,
                0.0
            ],
            "left": [
                -0.6563112735748291,
                -0.7544902563095093,
                0.0
            ]
        },
        "split": "new",
        "image_filename": "CLEVR_000035.png",
        "image_index": "000035"
    }
]