[
    {
        "referent": [
            "CLEVR_000084.png"
        ],
        "type": "direct contextual cancellation",
        "utterance": "Some large rubber cubes are on the right of the small rubber cylinders"
    },
    {
        "utterances": [
            "all_some_behind",
            "all_some_front",
            "all_all_right"
        ],
        "split": "new",
        "relationships": {
            "behind": [
                [
                    2
                ],
                [
                    0,
                    2,
                    6
                ],
                [],
                [
                    0,
                    1,
                    2,
                    6
                ],
                [
                    0,
                    1,
                    2,
                    3,
                    6
                ],
                [
                    0,
                    1,
                    2,
                    3,
                    4,
                    6
                ],
                [
                    0,
                    2
                ]
            ],
            "right": [
                [],
                [
                    0
                ],
                [
                    0,
                    1,
                    4
                ],
                [
                    0,
                    1,
                    2,
                    4,
                    5
                ],
                [
                    0,
                    1
                ],
                [
                    0,
                    1,
                    2,
                    4
                ],
                [
                    0,
                    1,
                    2,
                    3,
                    4,
                    5
                ]
            ],
            "front": [
                [
                    1,
                    3,
                    4,
                    5,
                    6
                ],
                [
                    3,
                    4,
                    5
                ],
                [
                    0,
                    1,
                    3,
                    4,
                    5,
                    6
                ],
                [
                    4,
                    5
                ],
                [
                    5
                ],
                [],
                [
                    1,
                    3,
                    4,
                    5
                ]
            ],
            "left": [
                [
                    1,
                    2,
                    3,
                    4,
                    5,
                    6
                ],
                [
                    2,
                    3,
                    4,
                    5,
                    6
                ],
                [
                    3,
                    5,
                    6
                ],
                [
                    6
                ],
                [
                    2,
                    3,
                    5,
                    6
                ],
                [
                    3,
                    6
                ],
                []
            ]
        },
        "image_index": "000084",
        "objects": [
            {
                "material": "rubber",
                "3d_coords": [
                    0.23246178030967712,
                    2.813197612762451,
                    0.699999988079071
                ],
                "shape": "cube",
                "color": "red",
                "size": "large",
                "rotation": 67.10486644377453,
                "pixel_coords": [
                    332,
                    103,
                    13.029765129089355
                ]
            },
            {
                "material": "rubber",
                "3d_coords": [
                    1.2886451482772827,
                    0.6233432292938232,
                    0.699999988079071
                ],
                "shape": "cube",
                "color": "yellow",
                "size": "large",
                "rotation": 22.998034581252647,
                "pixel_coords": [
                    302,
                    143,
                    11.062714576721191
                ]
            },
            {
                "material": "rubber",
                "3d_coords": [
                    -2.094926595687866,
                    1.6796270608901978,
                    0.3499999940395355
                ],
                "shape": "cylinder",
                "color": "green",
                "size": "small",
                "rotation": 352.4795380395815,
                "pixel_coords": [
                    236,
                    101,
                    14.093562126159668
                ]
            },
            {
                "material": "rubber",
                "3d_coords": [
                    -0.8069087862968445,
                    -2.578415870666504,
                    0.3499999940395355
                ],
                "shape": "cylinder",
                "color": "red",
                "size": "small",
                "rotation": 205.62791412258537,
                "pixel_coords": [
                    119,
                    170,
                    10.779398918151855
                ]
            },
            {
                "material": "metal",
                "3d_coords": [
                    2.26180362701416,
                    -0.7640272378921509,
                    0.3499999940395355
                ],
                "shape": "cylinder",
                "color": "gray",
                "size": "small",
                "rotation": 229.95376957790688,
                "pixel_coords": [
                    288,
                    199,
                    9.778924942016602
                ]
            },
            {
                "material": "rubber",
                "3d_coords": [
                    2.1436126232147217,
                    -2.90452241897583,
                    0.699999988079071
                ],
                "shape": "sphere",
                "color": "red",
                "size": "large",
                "rotation": 270.09949916594076,
                "pixel_coords": [
                    191,
                    225,
                    8.458379745483398
                ]
            },
            {
                "material": "metal",
                "3d_coords": [
                    -2.1113479137420654,
                    -2.5945770740509033,
                    0.3499999940395355
                ],
                "shape": "cylinder",
                "color": "blue",
                "size": "small",
                "rotation": 141.875296350093,
                "pixel_coords": [
                    89,
                    148,
                    11.640056610107422
                ]
            }
        ],
        "image_filename": "CLEVR_000084.png",
        "directions": {
            "above": [
                0.0,
                0.0,
                1.0
            ],
            "below": [
                -0.0,
                -0.0,
                -1.0
            ],
            "behind": [
                -0.754490315914154,
                0.6563112735748291,
                0.0
            ],
            "right": [
                0.6563112735748291,
                0.7544902563095093,
                -0.0
            ],
            "front": [
                0.754490315914154,
                -0.6563112735748291,
                -0.0
            ],
            "left": [
                -0.6563112735748291,
                -0.7544902563095093,
                0.0
            ]
        }
    },
    {
        "split": "new",
        "relationships": {
            "behind": [
                [],
                [
                    0,
                    2,
                    3
                ],
                [
                    0
                ],
                [
                    0,
                    2
                ]
            ],
            "right": [
                [
                    1,
                    2
                ],
                [],
                [
                    1
                ],
                [
                    0,
                    1,
                    2
                ]
            ],
            "front": [
                [
                    1,
                    2,
                    3
                ],
                [],
                [
                    1,
                    3
                ],
                [
                    1
                ]
            ],
            "left": [
                [
                    3
                ],
                [
                    0,
                    2,
                    3
                ],
                [
                    0,
                    3
                ],
                []
            ]
        },
        "image_index": "000085",
        "objects": [
            {
                "material": "metal",
                "3d_coords": [
                    -1.7643767595291138,
                    1.4935903549194336,
                    0.699999988079071
                ],
                "shape": "sphere",
                "color": "gray",
                "size": "large",
                "rotation": 166.8459877498357,
                "pixel_coords": [
                    240,
                    87,
                    12.644619941711426
                ]
            },
            {
                "material": "metal",
                "3d_coords": [
                    2.773951768875122,
                    0.62748122215271,
                    0.699999988079071
                ],
                "shape": "cylinder",
                "color": "yellow",
                "size": "large",
                "rotation": 236.58843664950007,
                "pixel_coords": [
                    370,
                    175,
                    9.153972625732422
                ]
            },
            {
                "material": "rubber",
                "3d_coords": [
                    0.3578483462333679,
                    0.2229171097278595,
                    0.699999988079071
                ],
                "shape": "sphere",
                "color": "green",
                "size": "large",
                "rotation": 125.79660859044262,
                "pixel_coords": [
                    260,
                    133,
                    10.529942512512207
                ]
            },
            {
                "material": "metal",
                "3d_coords": [
                    -0.28735876083374023,
                    -1.178849458694458,
                    0.3499999940395355
                ],
                "shape": "cube",
                "color": "red",
                "size": "small",
                "rotation": 22.825992373012575,
                "pixel_coords": [
                    185,
                    158,
                    10.351547241210938
                ]
            }
        ],
        "image_filename": "CLEVR_000085.png",
        "directions": {
            "above": [
                0.0,
                0.0,
                1.0
            ],
            "below": [
                -0.0,
                -0.0,
                -1.0
            ],
            "behind": [
                -0.754490315914154,
                0.6563112735748291,
                0.0
            ],
            "right": [
                0.6563112735748291,
                0.7544902563095093,
                -0.0
            ],
            "front": [
                0.754490315914154,
                -0.6563112735748291,
                -0.0
            ],
            "left": [
                -0.6563112735748291,
                -0.7544902563095093,
                0.0
            ]
        }
    },
    {
        "split": "new",
        "relationships": {
            "behind": [
                [
                    2
                ],
                [
                    0,
                    2
                ],
                [],
                [
                    0,
                    1,
                    2
                ]
            ],
            "right": [
                [
                    1,
                    2,
                    3
                ],
                [
                    2,
                    3
                ],
                [
                    3
                ],
                []
            ],
            "front": [
                [
                    1,
                    3
                ],
                [
                    3
                ],
                [
                    0,
                    1,
                    3
                ],
                []
            ],
            "left": [
                [],
                [
                    0
                ],
                [
                    0,
                    1
                ],
                [
                    0,
                    1,
                    2
                ]
            ]
        },
        "image_index": "000086",
        "objects": [
            {
                "material": "rubber",
                "3d_coords": [
                    -1.5939514636993408,
                    0.8130686283111572,
                    0.699999988079071
                ],
                "shape": "cube",
                "color": "blue",
                "size": "large",
                "rotation": 265.09487455130346,
                "pixel_coords": [
                    225,
                    100,
                    12.807539939880371
                ]
            },
            {
                "material": "rubber",
                "3d_coords": [
                    1.241478681564331,
                    0.004946565721184015,
                    0.699999988079071
                ],
                "shape": "cube",
                "color": "gray",
                "size": "large",
                "rotation": 132.49319976641888,
                "pixel_coords": [
                    280,
                    153,
                    10.446662902832031
                ]
            },
            {
                "material": "metal",
                "3d_coords": [
                    -1.0099414587020874,
                    2.566088914871216,
                    0.699999988079071
                ],
                "shape": "cube",
                "color": "green",
                "size": "large",
                "rotation": 296.4432090287338,
                "pixel_coords": [
                    293,
                    90,
                    13.37905216217041
                ]
            },
            {
                "material": "metal",
                "3d_coords": [
                    2.9238626956939697,
                    0.1581936627626419,
                    0.699999988079071
                ],
                "shape": "cube",
                "color": "purple",
                "size": "large",
                "rotation": 344.2466494499883,
                "pixel_coords": [
                    350,
                    185,
                    9.39454174041748
                ]
            }
        ],
        "image_filename": "CLEVR_000086.png",
        "directions": {
            "above": [
                0.0,
                0.0,
                1.0
            ],
            "below": [
                -0.0,
                -0.0,
                -1.0
            ],
            "behind": [
                -0.754490315914154,
                0.6563112735748291,
                0.0
            ],
            "right": [
                0.6563112735748291,
                0.7544902563095093,
                -0.0
            ],
            "front": [
                0.754490315914154,
                -0.6563112735748291,
                -0.0
            ],
            "left": [
                -0.6563112735748291,
                -0.7544902563095093,
                0.0
            ]
        }
    }
]